sagellm_dev_tools/__init__.py
sagellm_dev_tools/__init__.pyc
sagellm_dev_tools/checker.pyc
sagellm_dev_tools/cli.pyc
sagellm_dev_tools/constants.pyc
sagellm_dev_tools/fixer.pyc
sagellm_dev_tools/github_cli.pyc
sagellm_dev_tools/hooks_manager.pyc
sagellm_dev_tools/py.typed
sagellm_dev_tools/pytorch_manager.pyc
sagellm_dev_tools/repo_manager.pyc
sagellm_dev_tools/__pycache__/__init__.cpython-311.pyc
sagellm_dev_tools/__pycache__/checker.cpython-311.pyc
sagellm_dev_tools/__pycache__/cli.cpython-311-pytest-8.4.2.pyc
sagellm_dev_tools/__pycache__/cli.cpython-311.pyc
sagellm_dev_tools/__pycache__/constants.cpython-311.pyc
sagellm_dev_tools/__pycache__/fixer.cpython-311.pyc
sagellm_dev_tools/__pycache__/github_cli.cpython-311.pyc
sagellm_dev_tools/__pycache__/hooks_manager.cpython-311.pyc
sagellm_dev_tools/__pycache__/pytorch_manager.cpython-311.pyc
sagellm_dev_tools/__pycache__/repo_manager.cpython-311.pyc
sagellm_dev_tools/commands/__init__.pyc
sagellm_dev_tools/commands/fix.pyc
sagellm_dev_tools/commands/gh.pyc
sagellm_dev_tools/commands/hooks.pyc
sagellm_dev_tools/commands/pytorch.pyc
sagellm_dev_tools/commands/repo.pyc
sagellm_dev_tools/commands/__pycache__/__init__.cpython-311.pyc
sagellm_dev_tools/commands/__pycache__/fix.cpython-311.pyc
sagellm_dev_tools/commands/__pycache__/gh.cpython-311.pyc
sagellm_dev_tools/commands/__pycache__/hooks.cpython-311.pyc
sagellm_dev_tools/commands/__pycache__/pytorch.cpython-311.pyc
sagellm_dev_tools/commands/__pycache__/repo.cpython-311.pyc
sagellm_dev_tools/templates/ci_version_check.yml
sagellm_dev_tools/utils/__init__.pyc
sagellm_dev_tools/utils/constants.pyc
sagellm_dev_tools/utils/formatting.pyc
sagellm_dev_tools/utils/git.pyc
sagellm_dev_tools/utils/github.pyc
sagellm_dev_tools/utils/__pycache__/__init__.cpython-311.pyc
sagellm_dev_tools/utils/__pycache__/constants.cpython-311.pyc
sagellm_dev_tools/utils/__pycache__/formatting.cpython-311.pyc
sagellm_dev_tools/utils/__pycache__/git.cpython-311.pyc
isagellm_dev_tools-0.2.2.1.dist-info/METADATA
isagellm_dev_tools-0.2.2.1.dist-info/WHEEL
isagellm_dev_tools-0.2.2.1.dist-info/entry_points.txt
isagellm_dev_tools-0.2.2.1.dist-info/top_level.txt
isagellm_dev_tools-0.2.2.1.dist-info/RECORD
