Metadata-Version: 2.4
Name: isagellm-dev-tools
Version: 0.2.2.1
Summary: Developer tools for sageLLM multi-repository development
Author-email: IntelliStream Team <intellistream@outlook.com>
License: Proprietary
Project-URL: Homepage, https://github.com/intellistream/sagellm-dev-tools
Project-URL: Repository, https://github.com/intellistream/sagellm-dev-tools
Project-URL: Issues, https://github.com/intellistream/sagellm-dev-tools/issues
Keywords: llm,inference,developer-tools,sagellm
Classifier: Development Status :: 3 - Alpha
Classifier: Intended Audience :: Developers
Classifier: Programming Language :: Python :: 3
Classifier: Programming Language :: Python :: 3.10
Classifier: Programming Language :: Python :: 3.11
Classifier: Programming Language :: Python :: 3.12
Requires-Python: ==3.11.*
Requires-Dist: click>=8.1.0
Requires-Dist: rich>=13.0.0
Requires-Dist: PyYAML>=6.0
Requires-Dist: GitPython>=3.1.0
Requires-Dist: requests>=2.31.0
Provides-Extra: dev
Requires-Dist: pytest>=7.4.0; extra == "dev"
Requires-Dist: pytest-cov>=4.1.0; extra == "dev"
Requires-Dist: pytest-asyncio>=0.21.0; extra == "dev"
Requires-Dist: ruff>=0.8.0; extra == "dev"
Requires-Dist: mypy>=1.5.0; extra == "dev"
Requires-Dist: pre-commit>=3.3.0; extra == "dev"
